st_line_plotter/__init__.py
st_line_plotter/frontend/build/asset-manifest.json
st_line_plotter/frontend/build/index.html
st_line_plotter/frontend/build/precache-manifest.6279477322d7616ea3eaabbcb4ce811d.js
st_line_plotter/frontend/build/service-worker.js
st_line_plotter/frontend/build/static/js/2.eb731a1a.chunk.js
st_line_plotter/frontend/build/static/js/2.eb731a1a.chunk.js.LICENSE.txt
st_line_plotter/frontend/build/static/js/2.eb731a1a.chunk.js.map
st_line_plotter/frontend/build/static/js/main.a9c05652.chunk.js
st_line_plotter/frontend/build/static/js/main.a9c05652.chunk.js.map
st_line_plotter/frontend/build/static/js/runtime-main.11ec9aca.js
st_line_plotter/frontend/build/static/js/runtime-main.11ec9aca.js.map
st_line_plotter-0.0.10.dist-info/LICENSE
st_line_plotter-0.0.10.dist-info/METADATA
st_line_plotter-0.0.10.dist-info/WHEEL
st_line_plotter-0.0.10.dist-info/top_level.txt
st_line_plotter-0.0.10.dist-info/RECORD
